setup.py
elasticstat/__init__.py
elasticstat/elasticstat.py
elasticstat.egg-info/PKG-INFO
elasticstat.egg-info/SOURCES.txt
elasticstat.egg-info/dependency_links.txt
elasticstat.egg-info/entry_points.txt
elasticstat.egg-info/requires.txt
elasticstat.egg-info/top_level.txt