Metadata-Version: 1.1
Name: elasticstat
Version: 1.0.0
Summary: Real-time performance monitoring of an Elasticsearch cluster from the command line
Home-page: https://github.com/objectrocket/elasticstat
Author: Jeff Tharp
Author-email: jtharp@objectrocket.com
License: UNKNOWN
Download-URL: https://github.com/objectrocket/elasticstat/archive/1.0.0.tar.gz
Platform: UNKNOWN
